graph_mail_client/__init__.py
graph_mail_client/client.py
graph_mail_client/code_utils.py
graph_mail_client/config.py
graph_mail_client-0.1.0.dist-info/METADATA
graph_mail_client-0.1.0.dist-info/WHEEL
graph_mail_client-0.1.0.dist-info/top_level.txt
graph_mail_client-0.1.0.dist-info/RECORD
